context_engineering/__init__.py
context_engineering-0.1.0.dist-info/METADATA
context_engineering-0.1.0.dist-info/WHEEL
context_engineering-0.1.0.dist-info/RECORD
