Metadata-Version: 2.4
Name: context-engineering
Version: 0.1.0
Summary: A Python package for context engineering.
Requires-Python: >=3.12
